livekit/plugins/langchain/__init__.py
livekit/plugins/langchain/langgraph.py
livekit/plugins/langchain/py.typed
livekit/plugins/langchain/version.py
livekit_plugins_langchain-1.3.11.dist-info/METADATA
livekit_plugins_langchain-1.3.11.dist-info/WHEEL
livekit_plugins_langchain-1.3.11.dist-info/RECORD
